bin1_pkg/__init__.py
bin1_pkg/test27.py
bin1_pkg-0.1.0.dist-info/LICENSE
bin1_pkg-0.1.0.dist-info/METADATA
bin1_pkg-0.1.0.dist-info/WHEEL
bin1_pkg-0.1.0.dist-info/top_level.txt
bin1_pkg-0.1.0.dist-info/RECORD
