Metadata-Version: 2.1
Name: bin1-pkg
Version: 0.1.0
Summary: An example for teaching how to publish a Python package
Home-page: https://github.com/pypa/sampleproject
Author: Tian Song
Author-email: songtian@bit.edu.cn
License: UNKNOWN
Platform: UNKNOWN
Classifier: Programming Language :: Python :: 3
Classifier: License :: OSI Approved :: MIT License
Classifier: Operating System :: OS Independent
